{"cameraMode":{"drawMode":0,"name":"Shaded","section":"Shading Mode"},"sceneLighting":true,"audioPlay":false,"sceneViewState":{"m_AlwaysRefresh":false,"showFog":true,"showSkybox":true,"showFlares":true,"showImageEffects":true,"showParticleSystems":true,"showVisualEffectGraphs":true,"m_FxEnabled":true},"in2DMode":false,"pivot":{"x":182.83023071289063,"y":331.71075439453127,"z":0.0},"rotation":{"x":0.015231582336127758,"y":-0.10032293945550919,"z":0.001536452560685575,"w":0.9948351979255676},"size":2562.9267578125,"orthographic":false}